clang_tidy/__init__.py
clang_tidy/data/bin/clang-tidy.exe
clang_tidy/data/lib/clang/21/include/__clang_cuda_builtin_vars.h
clang_tidy/data/lib/clang/21/include/__clang_cuda_cmath.h
clang_tidy/data/lib/clang/21/include/__clang_cuda_complex_builtins.h
clang_tidy/data/lib/clang/21/include/__clang_cuda_device_functions.h
clang_tidy/data/lib/clang/21/include/__clang_cuda_intrinsics.h
clang_tidy/data/lib/clang/21/include/__clang_cuda_libdevice_declares.h
clang_tidy/data/lib/clang/21/include/__clang_cuda_math.h
clang_tidy/data/lib/clang/21/include/__clang_cuda_math_forward_declares.h
clang_tidy/data/lib/clang/21/include/__clang_cuda_runtime_wrapper.h
clang_tidy/data/lib/clang/21/include/__clang_cuda_texture_intrinsics.h
clang_tidy/data/lib/clang/21/include/__clang_hip_cmath.h
clang_tidy/data/lib/clang/21/include/__clang_hip_libdevice_declares.h
clang_tidy/data/lib/clang/21/include/__clang_hip_math.h
clang_tidy/data/lib/clang/21/include/__clang_hip_runtime_wrapper.h
clang_tidy/data/lib/clang/21/include/__clang_hip_stdlib.h
clang_tidy/data/lib/clang/21/include/__clang_spirv_builtins.h
clang_tidy/data/lib/clang/21/include/__stdarg___gnuc_va_list.h
clang_tidy/data/lib/clang/21/include/__stdarg___va_copy.h
clang_tidy/data/lib/clang/21/include/__stdarg_header_macro.h
clang_tidy/data/lib/clang/21/include/__stdarg_va_arg.h
clang_tidy/data/lib/clang/21/include/__stdarg_va_copy.h
clang_tidy/data/lib/clang/21/include/__stdarg_va_list.h
clang_tidy/data/lib/clang/21/include/__stddef_header_macro.h
clang_tidy/data/lib/clang/21/include/__stddef_max_align_t.h
clang_tidy/data/lib/clang/21/include/__stddef_null.h
clang_tidy/data/lib/clang/21/include/__stddef_nullptr_t.h
clang_tidy/data/lib/clang/21/include/__stddef_offsetof.h
clang_tidy/data/lib/clang/21/include/__stddef_ptrdiff_t.h
clang_tidy/data/lib/clang/21/include/__stddef_rsize_t.h
clang_tidy/data/lib/clang/21/include/__stddef_size_t.h
clang_tidy/data/lib/clang/21/include/__stddef_unreachable.h
clang_tidy-21.1.1.dist-info/METADATA
clang_tidy-21.1.1.dist-info/WHEEL
clang_tidy-21.1.1.dist-info/entry_points.txt
clang_tidy-21.1.1.dist-info/licenses/COPYING.md
clang_tidy-21.1.1.dist-info/licenses/LICENSE.md
clang_tidy-21.1.1.dist-info/RECORD
