Metadata-Version: 2.2
Name: clang-tidy
Version: 21.1.1
Summary: Clang-tidy is an LLVM-based code analyser tool
Author-Email: Dominic Kempf <ssc@iwr.uni-heidelberg.de>
License: Apache 2.0
Classifier: Programming Language :: C
Classifier: Programming Language :: C++
Classifier: Operating System :: OS Independent
Classifier: License :: OSI Approved :: Apache Software License
Classifier: Intended Audience :: Developers
Classifier: Topic :: Software Development :: Quality Assurance
Project-URL: Clang, http://clang.llvm.org/
Project-URL: Documentation, https://clang.llvm.org/extra/clang-tidy/index.html#clang-tidy
Project-URL: Download, https://github.com/llvm/llvm-project/releases
Project-URL: Source, https://github.com/ssciwr/clang-tidy-wheel
